household_account-0.3.1.dist-info/METADATA
household_account-0.3.1.dist-info/WHEEL
household_account-0.3.1.dist-info/entry_points.txt
household_account-0.3.1.dist-info/licenses/LICENSE
household_account/__init__.py
household_account/where_now.py
household_account-0.3.1.dist-info/RECORD
