Metadata-Version: 2.1
Name: Household-Account
Version: 0.3.1
Summary: Save Money in Times of High Inflation
Author-Email: heejin131 <journeyjean131@gmail.com>
License: MIT
Requires-Python: >=3.10
Requires-Dist: typer>=0.15.1
